cohesive/__init__.py
cohesive/client.py
cohesive/sample.py
cohesive/sample1.py
cohesive/util.py
cohesivesdk-0.0.1.dist-info/WHEEL
cohesivesdk-0.0.1.dist-info/METADATA
cohesivesdk-0.0.1.dist-info/RECORD
